{
    "Find or start a conversation":"Tìm hoặc bắt đầu cuộc trò chuyện",
    "Friends":"Bạn bè",
    "Online":"Trực tuyến",
    "Offline": "Ngoại tuyến",
    "All": "Tất cả",
    "Add friend": "Thêm Bạn",
    "Direct Messages": "TIN NHẮN TRỰC TIẾP",
    "User logged out": "Người dùng đã đăng xuất",
    "Logout failed:": "Đăng xuất thất bại",
    "Saving profile:": "Đang lưu hồ sơ",
    "Passwords don't match!": "Mật khẩu không trùng khớp",
    "Changing password": "Đang đổi mật khẩu",
    "Edit Profile": "Chỉnh sửa Hồ sơ",
    "Change Password": "Đổi Mật khẩu",
    "My Account": "Tài khoản của tôi",
    "Username": "Tên đăng nhập",
    "Cancel": "Hủy",
    "Save Changes": "Lưu thay đổi",
    "Current Password": "Mật khẩu hiện tại",
    "New Password": "Mật khẩu mới",
    "Confirm New Password": "Xác nhận Mật khẩu mới",
    "USER SETTINGS": "CÀI ĐẶT NGƯỜI DÙNG",
    "Logout": "Đăng xuất",
    "Edit User Profile": "Chỉnh sửa Hồ sơ người dùng",
    "Password and Authentication": "Mật khẩu và Xác thực",
    "Something went wrong. Please try again.": "Có gì đó đã ngưng hoạt động. Làm ơn thử lại.",
    "Passwords do not match.": "Các Mật khẩu không trùng.",
    "Update Password Successful!": "Cập nhật Mật khẩu thành công!",
    "You can log in now!": "Bạn có thể đăng nhập ngay bây giờ!",
    "Invalid Email": "Email không hợp lệ",
    "Password must be filled": "Mật khẩu không được để trống",
    "Failed to login:":"Đăng nhập thất bại:",
    "Google Login:": "Đăng nhập bằng Google",
    "Failed to login Google account": "Đăng nhập Google thất bại:",
    "Facebook Login:": "Đăng nhập bằng Facebook",
    "Failed to login Facebook account": "Đăng nhập Facebook thất bại:",
    "Welcome back!": "Chào mừng trở lại!",
    "We are glad to see you again!": "Chúng tôi rất vui khi gặp lại bạn!",
    "Login": "Đăng nhập",
    "Forgot passwork?": "Quên mật khẩu?",
    "Need an account?": "Chưa có tài khoản?",
    "Reset password": "Reset lại mật khẩu",
    "Do the following steps to reset your account": "Làm theo các bược sau để reset lại tài khoản của bạn.",
    "Confirm": "Xác nhận",
    "Code confirm": "Xác nhận mã",
    "Change passwork confirm": "Xác nhận thay đổi mật khẩu",
    "Invalid phone number": "Số điện thoại không hợp lệ",
    "Password not matched": "Mật khẩu xác nhận không khớp",
    "Registration success!": "Đăng ký thành công",
    "Registration fail!": "Đăng ký thất bại",
    "Join us now": "Tham gia ngay",
    "Register to connect with friends and EchoChat communities": "Đăng ký để kết nối với bạn bè và cộng đồng EchoChat",
    "Phone number": "Số điện thoại",
    "Confirm Password": "Xác nhận mật khẩu",
    "Have an account?": "Đã có tài khoản?",
    "Dark": "Tối",
    "dark": "tối",
    "Light": "Sáng",
    "light": "sáng",
    "You": "Bạn",
    "This is the beginning of your direct message history with": "Đây là sự bắt đầu của lịch sử nhắn tin trực tiếp của bạn với",
    "Message @": "Gửi tin nhắn cho @",
    "Profile": "Hồ sơ",
    "Unfriend": "Hủy kết bạn",
    "Block": "Chặn",
    "Message": "Tin nhắn",
    "Add Friend": "Thêm bạn",
    "About Me": "Về bản thân tôi",
    "Mutual Friends": "Bạn thân",
    "Mutual Servers": "Máy chủ yêu thích",
    "There aren't any online friends now. Please come back later!" : "Không có bạn bè nào trực tuyến vào lúc này. Hãy quay lại sau!",
    "Active": "Đang hoạt động",
    "idle": "Chờ",
    "Create Your Server": "Tạo Máy chủ của bạn",
    "Your server is where you and your friends hang out. Make yours and start talking.": "Máy chủ là nơi mà bạn giao lưu với bạn bè của mình. Hãy tạo máy chủ của riêng bạn và bắt đầu trò chuyện.",
    "Create My Own": "Tạo mẫu riêng",
    "Have an invite already?": "Bạn đã nhận được lời mời rồi?",
    "Join a server": "Tham gia Máy chủ",
    "Customize Your Server": "Tùy chỉnh Máy chủ của bạn",
    "Give your new server a personality with a name and an icon. You can always change it later.": "Hãy tạo cá tính cho máy chủ mới của bạn bằng việc đặt tên và gắn icon. Bạn luôn có thể chỉnh lại sau.",
    "UPLOAD": "TẢI LÊN",
    "SERVER NAME": "TÊN MÁY CHỦ",
    "Back": "Quay lại",
    "Enter an invite below to join an existing server": "Nhập lời mời để tham gia mmáy chủ được tạo sẵn",
    "INVITE LINK": "ĐƯỜNG DẪN LỜI MỜI",
    "INVITES SHOULD LOOK LIKE": "LỜI MỜI NÊN TRÔNG GIỐNG NHƯ SAU",
    "Don't have an invite?": "Bạn không có lời mời?",
    "Join Server":"Tham gia máy chủ"
}